Bignumber_to_PersianString_sama/BigNumFunc.py
Bignumber_to_PersianString_sama/__init__.py
Bignumber_to_PersianString_sama/main.py
bignumber_to_persianstring_sama-0.0.1.dist-info/METADATA
bignumber_to_persianstring_sama-0.0.1.dist-info/WHEEL
bignumber_to_persianstring_sama-0.0.1.dist-info/licenses/Licence
bignumber_to_persianstring_sama-0.0.1.dist-info/RECORD
